README.md
setup.py
test/__init__.py
test/test_annealer_basic_builder.py
test/test_annealing_optimizer.py
test/test_consecutive_non_improvement.py
test/test_cross_validator.py
test/test_genetic_optimizer.py
test/test_genetic_optimizer_basic_builder.py
test/test_numpy_rng.py
test/test_optimizer_basic.py
test/test_optimizer_basic_builder.py
test/test_optimizer_basic_restart.py
test/test_prebuilt_optimizers.py
test/test_python_base_rng.py
test/test_roulette_wheel_comparer.py
test/test_single_crossover_genome_builder.py
test/test_time_series_cross_validator.py
test/test_train_test_validator.py
test/test_transform_bitstring_to_layers_tuple.py
test/test_uniform_crossover_genome_builder.py
tunepy2/__init__.py
tunepy2.egg-info/PKG-INFO
tunepy2.egg-info/SOURCES.txt
tunepy2.egg-info/dependency_links.txt
tunepy2.egg-info/requires.txt
tunepy2.egg-info/top_level.txt
tunepy2/comparison/__init__.py
tunepy2/comparison/roulette_wheel_comparer.py
tunepy2/convergence/__init__.py
tunepy2/convergence/annealing_schedules.py
tunepy2/convergence/simple_convergence.py
tunepy2/genome_factory/__init__.py
tunepy2/genome_factory/ga_genome_factory.py
tunepy2/genome_factory/hill_climb_genome_factory.py
tunepy2/genome_factory/neighbor_genome_factory.py
tunepy2/genome_factory/random_genome_factory.py
tunepy2/interfaces/__init__.py
tunepy2/interfaces/abstract_convergence_criterion.py
tunepy2/interfaces/abstract_genome_comparer.py
tunepy2/interfaces/abstract_genome_factory.py
tunepy2/interfaces/abstract_learner.py
tunepy2/interfaces/abstract_learner_factory.py
tunepy2/interfaces/abstract_optimizer.py
tunepy2/interfaces/abstract_optimizer_builder.py
tunepy2/interfaces/abstract_rng.py
tunepy2/interfaces/abstract_validator.py
tunepy2/interfaces/stubs/__init__.py
tunepy2/interfaces/stubs/stub_convergence_criteria.py
tunepy2/interfaces/stubs/stub_genome_factories.py
tunepy2/interfaces/stubs/stub_learners.py
tunepy2/interfaces/stubs/stub_model_comparers.py
tunepy2/interfaces/stubs/stub_model_factories.py
tunepy2/interfaces/stubs/stub_optimizers.py
tunepy2/interfaces/stubs/stub_rngs.py
tunepy2/interfaces/stubs/stub_validators.py
tunepy2/internal/__init__.py
