Metadata-Version: 2.1
Name: tunepy2
Version: 0.0.3
Summary: A package containing a set of bitstring optimizers.
Home-page: https://github.com/efortner/tunepy
Author: Ethan Fortner
Author-email: ethan.fortner@icloud.com
License: UNKNOWN
Platform: UNKNOWN
Classifier: Programming Language :: Python :: 3.7
Classifier: License :: OSI Approved :: MIT License
Classifier: Operating System :: OS Independent
Requires-Python: >=3.7
